lexiquery/__init__.py
lexiquery/astnodes.py
lexiquery/core.py
lexiquery/evaluator.py
lexiquery/exceptions.py
lexiquery/grammar.py
lexiquery/parser.py
lexiquery/tokenizer.py
lexiquery/utils.py
lexiquery-0.2.1.dist-info/METADATA
lexiquery-0.2.1.dist-info/WHEEL
lexiquery-0.2.1.dist-info/licenses/LICENSE
lexiquery-0.2.1.dist-info/RECORD
