Metadata-Version: 2.4
Name: lexiquery
Version: 0.2.1
Summary: A small boolean + positional query engine with a proper parser.
Author: Hou Yafei
License: MIT
License-File: LICENSE
Keywords: boolean,parser,positional,query
Classifier: License :: OSI Approved :: MIT License
Classifier: Programming Language :: Python :: 3
Classifier: Topic :: Text Processing
Requires-Python: >=3.9
Provides-Extra: dev
Requires-Dist: mypy>=1.10; extra == 'dev'
Requires-Dist: pytest>=8; extra == 'dev'
Requires-Dist: ruff>=0.6; extra == 'dev'
